[
    {
        "team": [
            "KENJI",
            "MOE",
            "RICO"
        ],
        "games_played": 383,
        "win_rate": 0.6840731070496083
    },
    {
        "team": [
            "MOE",
            "RICO",
            "SURGE"
        ],
        "games_played": 300,
        "win_rate": 0.64
    },
    {
        "team": [
            "KENJI",
            "MOE",
            "SURGE"
        ],
        "games_played": 377,
        "win_rate": 0.6127320954907162
    },
    {
        "team": [
            "FRANK",
            "KENJI",
            "RICO"
        ],
        "games_played": 508,
        "win_rate": 0.6062992125984252
    },
    {
        "team": [
            "FRANK",
            "RICO",
            "SURGE"
        ],
        "games_played": 581,
        "win_rate": 0.5834767641996558
    },
    {
        "team": [
            "JACKY",
            "MORTIS",
            "SURGE"
        ],
        "games_played": 492,
        "win_rate": 0.5609756097560976
    },
    {
        "team": [
            "KENJI",
            "STU",
            "SURGE"
        ],
        "games_played": 335,
        "win_rate": 0.5552238805970149
    },
    {
        "team": [
            "DYNAMIKE",
            "EDGAR",
            "KENJI"
        ],
        "games_played": 308,
        "win_rate": 0.5551948051948052
    },
    {
        "team": [
            "FANG",
            "FRANK",
            "MORTIS"
        ],
        "games_played": 333,
        "win_rate": 0.5495495495495496
    },
    {
        "team": [
            "FRANK",
            "MORTIS",
            "STU"
        ],
        "games_played": 497,
        "win_rate": 0.5492957746478874
    },
    {
        "team": [
            "BIBI",
            "FRANK",
            "SURGE"
        ],
        "games_played": 670,
        "win_rate": 0.5492537313432836
    },
    {
        "team": [
            "BIBI",
            "DYNAMIKE",
            "SURGE"
        ],
        "games_played": 651,
        "win_rate": 0.5453149001536098
    },
    {
        "team": [
            "BIBI",
            "RICO",
            "SURGE"
        ],
        "games_played": 540,
        "win_rate": 0.5444444444444444
    },
    {
        "team": [
            "DYNAMIKE",
            "FRANK",
            "SURGE"
        ],
        "games_played": 673,
        "win_rate": 0.5438335809806835
    },
    {
        "team": [
            "CLANCY",
            "KENJI",
            "MORTIS"
        ],
        "games_played": 333,
        "win_rate": 0.5435435435435435
    },
    {
        "team": [
            "BIBI",
            "JACKY",
            "MORTIS"
        ],
        "games_played": 350,
        "win_rate": 0.5342857142857143
    },
    {
        "team": [
            "FRANK",
            "STU",
            "SURGE"
        ],
        "games_played": 307,
        "win_rate": 0.5342019543973942
    },
    {
        "team": [
            "KENJI",
            "MORTIS",
            "RICO"
        ],
        "games_played": 836,
        "win_rate": 0.5311004784688995
    },
    {
        "team": [
            "BIBI",
            "DYNAMIKE",
            "KENJI"
        ],
        "games_played": 586,
        "win_rate": 0.5307167235494881
    },
    {
        "team": [
            "KENJI",
            "RICO",
            "SURGE"
        ],
        "games_played": 788,
        "win_rate": 0.5304568527918782
    },
    {
        "team": [
            "BIBI",
            "BUZZ",
            "MORTIS"
        ],
        "games_played": 527,
        "win_rate": 0.5294117647058824
    },
    {
        "team": [
            "BUZZ",
            "FRANK",
            "MORTIS"
        ],
        "games_played": 463,
        "win_rate": 0.5291576673866091
    },
    {
        "team": [
            "BIBI",
            "DYNAMIKE",
            "FRANK"
        ],
        "games_played": 616,
        "win_rate": 0.525974025974026
    },
    {
        "team": [
            "BIBI",
            "FRANK",
            "KENJI"
        ],
        "games_played": 613,
        "win_rate": 0.5220228384991843
    },
    {
        "team": [
            "RICO",
            "STU",
            "SURGE"
        ],
        "games_played": 350,
        "win_rate": 0.52
    },
    {
        "team": [
            "FANG",
            "MORTIS",
            "SURGE"
        ],
        "games_played": 480,
        "win_rate": 0.5166666666666667
    },
    {
        "team": [
            "MOE",
            "MORTIS",
            "SURGE"
        ],
        "games_played": 331,
        "win_rate": 0.513595166163142
    },
    {
        "team": [
            "BIBI",
            "FRANK",
            "MORTIS"
        ],
        "games_played": 1064,
        "win_rate": 0.5131578947368421
    },
    {
        "team": [
            "BIBI",
            "KENJI",
            "RICO"
        ],
        "games_played": 482,
        "win_rate": 0.5124481327800829
    },
    {
        "team": [
            "BIBI",
            "MORTIS",
            "STU"
        ],
        "games_played": 516,
        "win_rate": 0.5116279069767442
    },
    {
        "team": [
            "BIBI",
            "KENJI",
            "SURGE"
        ],
        "games_played": 518,
        "win_rate": 0.5115830115830116
    },
    {
        "team": [
            "FRANK",
            "JACKY",
            "MORTIS"
        ],
        "games_played": 363,
        "win_rate": 0.509641873278237
    },
    {
        "team": [
            "BIBI",
            "FRANK",
            "RICO"
        ],
        "games_played": 472,
        "win_rate": 0.5084745762711864
    },
    {
        "team": [
            "FANG",
            "KENJI",
            "MORTIS"
        ],
        "games_played": 302,
        "win_rate": 0.5066225165562914
    },
    {
        "team": [
            "DYNAMIKE",
            "STU",
            "SURGE"
        ],
        "games_played": 374,
        "win_rate": 0.5053475935828877
    },
    {
        "team": [
            "DYNAMIKE",
            "EL PRIMO",
            "SURGE"
        ],
        "games_played": 309,
        "win_rate": 0.5048543689320388
    },
    {
        "team": [
            "DYNAMIKE",
            "RICO",
            "SURGE"
        ],
        "games_played": 785,
        "win_rate": 0.5044585987261146
    },
    {
        "team": [
            "FRANK",
            "MORTIS",
            "SURGE"
        ],
        "games_played": 1093,
        "win_rate": 0.5041171088746569
    },
    {
        "team": [
            "DYNAMIKE",
            "JACKY",
            "MORTIS"
        ],
        "games_played": 442,
        "win_rate": 0.502262443438914
    },
    {
        "team": [
            "KENJI",
            "MORTIS",
            "SURGE"
        ],
        "games_played": 1200,
        "win_rate": 0.4975
    },
    {
        "team": [
            "FRANK",
            "MORTIS",
            "RICO"
        ],
        "games_played": 904,
        "win_rate": 0.49557522123893805
    },
    {
        "team": [
            "DYNAMIKE",
            "JACKY",
            "SURGE"
        ],
        "games_played": 342,
        "win_rate": 0.49415204678362573
    },
    {
        "team": [
            "FRANK",
            "JACKY",
            "KENJI"
        ],
        "games_played": 305,
        "win_rate": 0.4918032786885246
    },
    {
        "team": [
            "DYNAMIKE",
            "KENJI",
            "SURGE"
        ],
        "games_played": 677,
        "win_rate": 0.49039881831610044
    },
    {
        "team": [
            "EL PRIMO",
            "FRANK",
            "MORTIS"
        ],
        "games_played": 402,
        "win_rate": 0.4900497512437811
    },
    {
        "team": [
            "MORTIS",
            "RICO",
            "SURGE"
        ],
        "games_played": 1129,
        "win_rate": 0.48892825509300264
    },
    {
        "team": [
            "FRANK",
            "KENJI",
            "MORTIS"
        ],
        "games_played": 922,
        "win_rate": 0.4880694143167028
    },
    {
        "team": [
            "MORTIS",
            "NITA",
            "SURGE"
        ],
        "games_played": 301,
        "win_rate": 0.4850498338870432
    },
    {
        "team": [
            "EDGAR",
            "MORTIS",
            "SURGE"
        ],
        "games_played": 674,
        "win_rate": 0.4836795252225519
    },
    {
        "team": [
            "JACKY",
            "MORTIS",
            "RICO"
        ],
        "games_played": 342,
        "win_rate": 0.4824561403508772
    },
    {
        "team": [
            "EL PRIMO",
            "MORTIS",
            "RICO"
        ],
        "games_played": 392,
        "win_rate": 0.47959183673469385
    },
    {
        "team": [
            "BIBI",
            "DYNAMIKE",
            "RICO"
        ],
        "games_played": 487,
        "win_rate": 0.47433264887063653
    },
    {
        "team": [
            "MORTIS",
            "STU",
            "SURGE"
        ],
        "games_played": 679,
        "win_rate": 0.4742268041237113
    },
    {
        "team": [
            "BUZZ",
            "MORTIS",
            "RICO"
        ],
        "games_played": 445,
        "win_rate": 0.47191011235955055
    },
    {
        "team": [
            "DYNAMIKE",
            "KENJI",
            "RICO"
        ],
        "games_played": 562,
        "win_rate": 0.47153024911032027
    },
    {
        "team": [
            "JACKY",
            "KENJI",
            "MORTIS"
        ],
        "games_played": 355,
        "win_rate": 0.4704225352112676
    },
    {
        "team": [
            "BUZZ",
            "MORTIS",
            "SURGE"
        ],
        "games_played": 577,
        "win_rate": 0.4696707105719237
    },
    {
        "team": [
            "BIBI",
            "KENJI",
            "MORTIS"
        ],
        "games_played": 1024,
        "win_rate": 0.46875
    },
    {
        "team": [
            "CLANCY",
            "DYNAMIKE",
            "MORTIS"
        ],
        "games_played": 392,
        "win_rate": 0.46683673469387754
    },
    {
        "team": [
            "COLT",
            "MORTIS",
            "SURGE"
        ],
        "games_played": 510,
        "win_rate": 0.4647058823529412
    },
    {
        "team": [
            "COLT",
            "FRANK",
            "MORTIS"
        ],
        "games_played": 431,
        "win_rate": 0.46403712296983757
    },
    {
        "team": [
            "BIBI",
            "DYNAMIKE",
            "MORTIS"
        ],
        "games_played": 1430,
        "win_rate": 0.458041958041958
    },
    {
        "team": [
            "EL PRIMO",
            "MORTIS",
            "SURGE"
        ],
        "games_played": 540,
        "win_rate": 0.4537037037037037
    },
    {
        "team": [
            "EDGAR",
            "FRANK",
            "MORTIS"
        ],
        "games_played": 602,
        "win_rate": 0.45348837209302323
    },
    {
        "team": [
            "MORTIS",
            "RICO",
            "STU"
        ],
        "games_played": 471,
        "win_rate": 0.45222929936305734
    },
    {
        "team": [
            "FRANK",
            "KENJI",
            "SURGE"
        ],
        "games_played": 774,
        "win_rate": 0.45219638242894056
    },
    {
        "team": [
            "DYNAMIKE",
            "MORTIS",
            "SHELLY"
        ],
        "games_played": 348,
        "win_rate": 0.4511494252873563
    },
    {
        "team": [
            "BIBI",
            "EDGAR",
            "MORTIS"
        ],
        "games_played": 606,
        "win_rate": 0.4504950495049505
    },
    {
        "team": [
            "BIBI",
            "COLT",
            "MORTIS"
        ],
        "games_played": 462,
        "win_rate": 0.45021645021645024
    },
    {
        "team": [
            "DYNAMIKE",
            "MORTIS",
            "NITA"
        ],
        "games_played": 315,
        "win_rate": 0.44761904761904764
    },
    {
        "team": [
            "BIBI",
            "EL PRIMO",
            "MORTIS"
        ],
        "games_played": 391,
        "win_rate": 0.4475703324808184
    },
    {
        "team": [
            "CLANCY",
            "MORTIS",
            "SURGE"
        ],
        "games_played": 320,
        "win_rate": 0.446875
    },
    {
        "team": [
            "DYNAMIKE",
            "MORTIS",
            "STU"
        ],
        "games_played": 596,
        "win_rate": 0.4429530201342282
    },
    {
        "team": [
            "COLT",
            "KENJI",
            "MORTIS"
        ],
        "games_played": 459,
        "win_rate": 0.4422657952069717
    },
    {
        "team": [
            "DYNAMIKE",
            "FRANK",
            "KENJI"
        ],
        "games_played": 498,
        "win_rate": 0.44176706827309237
    },
    {
        "team": [
            "EDGAR",
            "MORTIS",
            "RICO"
        ],
        "games_played": 499,
        "win_rate": 0.4408817635270541
    },
    {
        "team": [
            "BUZZ",
            "DYNAMIKE",
            "MORTIS"
        ],
        "games_played": 671,
        "win_rate": 0.4396423248882265
    },
    {
        "team": [
            "FANG",
            "MORTIS",
            "RICO"
        ],
        "games_played": 314,
        "win_rate": 0.43630573248407645
    },
    {
        "team": [
            "DYNAMIKE",
            "KENJI",
            "MORTIS"
        ],
        "games_played": 1077,
        "win_rate": 0.43454038997214484
    },
    {
        "team": [
            "BIBI",
            "MORTIS",
            "RICO"
        ],
        "games_played": 801,
        "win_rate": 0.4307116104868914
    },
    {
        "team": [
            "DYNAMIKE",
            "FRANK",
            "RICO"
        ],
        "games_played": 422,
        "win_rate": 0.42890995260663506
    },
    {
        "team": [
            "DYNAMIKE",
            "MORTIS",
            "SURGE"
        ],
        "games_played": 1603,
        "win_rate": 0.42732376793512167
    },
    {
        "team": [
            "BIBI",
            "MORTIS",
            "SURGE"
        ],
        "games_played": 1152,
        "win_rate": 0.4253472222222222
    },
    {
        "team": [
            "COLT",
            "MORTIS",
            "RICO"
        ],
        "games_played": 435,
        "win_rate": 0.42298850574712643
    },
    {
        "team": [
            "DYNAMIKE",
            "EDGAR",
            "SURGE"
        ],
        "games_played": 362,
        "win_rate": 0.42265193370165743
    },
    {
        "team": [
            "DYNAMIKE",
            "FANG",
            "MORTIS"
        ],
        "games_played": 515,
        "win_rate": 0.42135922330097086
    },
    {
        "team": [
            "DYNAMIKE",
            "EDGAR",
            "MORTIS"
        ],
        "games_played": 927,
        "win_rate": 0.42071197411003236
    },
    {
        "team": [
            "DYNAMIKE",
            "EL PRIMO",
            "MORTIS"
        ],
        "games_played": 583,
        "win_rate": 0.4202401372212693
    },
    {
        "team": [
            "EL PRIMO",
            "KENJI",
            "MORTIS"
        ],
        "games_played": 356,
        "win_rate": 0.4157303370786517
    },
    {
        "team": [
            "KENJI",
            "MORTIS",
            "STU"
        ],
        "games_played": 382,
        "win_rate": 0.41361256544502617
    },
    {
        "team": [
            "COLT",
            "DYNAMIKE",
            "MORTIS"
        ],
        "games_played": 670,
        "win_rate": 0.41194029850746267
    },
    {
        "team": [
            "DYNAMIKE",
            "FRANK",
            "MORTIS"
        ],
        "games_played": 1109,
        "win_rate": 0.41118124436429215
    },
    {
        "team": [
            "DARRYL",
            "MORTIS",
            "SURGE"
        ],
        "games_played": 318,
        "win_rate": 0.4025157232704403
    },
    {
        "team": [
            "DARRYL",
            "DYNAMIKE",
            "MORTIS"
        ],
        "games_played": 353,
        "win_rate": 0.40226628895184136
    },
    {
        "team": [
            "DYNAMIKE",
            "MORTIS",
            "RICO"
        ],
        "games_played": 1071,
        "win_rate": 0.38095238095238093
    },
    {
        "team": [
            "BUZZ",
            "EDGAR",
            "MORTIS"
        ],
        "games_played": 300,
        "win_rate": 0.38
    },
    {
        "team": [
            "BUZZ",
            "KENJI",
            "MORTIS"
        ],
        "games_played": 445,
        "win_rate": 0.37303370786516854
    },
    {
        "team": [
            "EDGAR",
            "KENJI",
            "MORTIS"
        ],
        "games_played": 528,
        "win_rate": 0.36742424242424243
    },
    {
        "team": [
            "COLT",
            "DYNAMIKE",
            "SURGE"
        ],
        "games_played": 345,
        "win_rate": 0.3536231884057971
    }
]