[
    {
        "brawler": "JUJU",
        "games_played": 5478,
        "win_rate": 0.5761226725082147
    },
    {
        "brawler": "LARRY & LAWRIE",
        "games_played": 51299,
        "win_rate": 0.5742412132790113
    },
    {
        "brawler": "BARLEY",
        "games_played": 37460,
        "win_rate": 0.5622530699412707
    },
    {
        "brawler": "WILLOW",
        "games_played": 12489,
        "win_rate": 0.5589718952678357
    },
    {
        "brawler": "LOU",
        "games_played": 5393,
        "win_rate": 0.5583163359910995
    },
    {
        "brawler": "CORDELIUS",
        "games_played": 40320,
        "win_rate": 0.5565724206349206
    },
    {
        "brawler": "JACKY",
        "games_played": 110880,
        "win_rate": 0.5482593795093795
    },
    {
        "brawler": "MOE",
        "games_played": 77228,
        "win_rate": 0.5479359817682706
    },
    {
        "brawler": "HANK",
        "games_played": 11661,
        "win_rate": 0.5432638710230684
    },
    {
        "brawler": "RUFFS",
        "games_played": 5469,
        "win_rate": 0.5432437374291461
    },
    {
        "brawler": "SAM",
        "games_played": 6418,
        "win_rate": 0.5384855095045186
    },
    {
        "brawler": "DRACO",
        "games_played": 11581,
        "win_rate": 0.5361367757533891
    },
    {
        "brawler": "NITA",
        "games_played": 86760,
        "win_rate": 0.5354195481788843
    },
    {
        "brawler": "ASH",
        "games_played": 3149,
        "win_rate": 0.5350905049221976
    },
    {
        "brawler": "MAISIE",
        "games_played": 23192,
        "win_rate": 0.535012073128665
    },
    {
        "brawler": "BULL",
        "games_played": 39605,
        "win_rate": 0.5334679964650928
    },
    {
        "brawler": "R-T",
        "games_played": 2182,
        "win_rate": 0.5293308890925756
    },
    {
        "brawler": "CHARLIE",
        "games_played": 1691,
        "win_rate": 0.527498521584861
    },
    {
        "brawler": "SANDY",
        "games_played": 24016,
        "win_rate": 0.5248167888074617
    },
    {
        "brawler": "FRANK",
        "games_played": 283812,
        "win_rate": 0.5219652445985371
    },
    {
        "brawler": "CARL",
        "games_played": 9882,
        "win_rate": 0.5202388180530257
    },
    {
        "brawler": "ROSA",
        "games_played": 2879,
        "win_rate": 0.5192775269190691
    },
    {
        "brawler": "CLANCY",
        "games_played": 66836,
        "win_rate": 0.5168023221018613
    },
    {
        "brawler": "BUSTER",
        "games_played": 12323,
        "win_rate": 0.5135924693662257
    },
    {
        "brawler": "OTIS",
        "games_played": 4719,
        "win_rate": 0.5128205128205128
    },
    {
        "brawler": "EL PRIMO",
        "games_played": 143478,
        "win_rate": 0.5110957777498989
    },
    {
        "brawler": "KENJI",
        "games_played": 304451,
        "win_rate": 0.5099769749483497
    },
    {
        "brawler": "SURGE",
        "games_played": 310511,
        "win_rate": 0.5090962961054519
    },
    {
        "brawler": "RICO",
        "games_played": 504828,
        "win_rate": 0.5090010855182359
    },
    {
        "brawler": "GRIFF",
        "games_played": 15922,
        "win_rate": 0.5089812837583219
    },
    {
        "brawler": "BIBI",
        "games_played": 274842,
        "win_rate": 0.5084957903086137
    },
    {
        "brawler": "TARA",
        "games_played": 32562,
        "win_rate": 0.5003992383760212
    },
    {
        "brawler": "AMBER",
        "games_played": 2572,
        "win_rate": 0.49922239502332816
    },
    {
        "brawler": "DYNAMIKE",
        "games_played": 389021,
        "win_rate": 0.49726878497561827
    },
    {
        "brawler": "DARRYL",
        "games_played": 55897,
        "win_rate": 0.49660983594826197
    },
    {
        "brawler": "GRAY",
        "games_played": 5273,
        "win_rate": 0.49535368860231366
    },
    {
        "brawler": "BERRY",
        "games_played": 11247,
        "win_rate": 0.49257579799057527
    },
    {
        "brawler": "BUZZ",
        "games_played": 118181,
        "win_rate": 0.49249879422242154
    },
    {
        "brawler": "EVE",
        "games_played": 384,
        "win_rate": 0.4921875
    },
    {
        "brawler": "GALE",
        "games_played": 52683,
        "win_rate": 0.491088206821935
    },
    {
        "brawler": "SQUEAK",
        "games_played": 7488,
        "win_rate": 0.49011752136752135
    },
    {
        "brawler": "TICK",
        "games_played": 100480,
        "win_rate": 0.4871417197452229
    },
    {
        "brawler": "MICO",
        "games_played": 4970,
        "win_rate": 0.4869215291750503
    },
    {
        "brawler": "STU",
        "games_played": 134704,
        "win_rate": 0.4858356099299204
    },
    {
        "brawler": "DOUG",
        "games_played": 9722,
        "win_rate": 0.4855996708496194
    },
    {
        "brawler": "MELODIE",
        "games_played": 11955,
        "win_rate": 0.4849853617733166
    },
    {
        "brawler": "CHESTER",
        "games_played": 30316,
        "win_rate": 0.4847605224963715
    },
    {
        "brawler": "MAX",
        "games_played": 19993,
        "win_rate": 0.48281898664532585
    },
    {
        "brawler": "SPROUT",
        "games_played": 6981,
        "win_rate": 0.48187938690731985
    },
    {
        "brawler": "SPIKE",
        "games_played": 33120,
        "win_rate": 0.4813707729468599
    },
    {
        "brawler": "PENNY",
        "games_played": 6417,
        "win_rate": 0.47981923016986133
    },
    {
        "brawler": "MR. P",
        "games_played": 1573,
        "win_rate": 0.4755244755244755
    },
    {
        "brawler": "JANET",
        "games_played": 801,
        "win_rate": 0.47191011235955055
    },
    {
        "brawler": "FANG",
        "games_played": 68733,
        "win_rate": 0.4715056814048565
    },
    {
        "brawler": "GROM",
        "games_played": 10492,
        "win_rate": 0.47045367899351886
    },
    {
        "brawler": "BEA",
        "games_played": 3013,
        "win_rate": 0.46996349153667444
    },
    {
        "brawler": "PAM",
        "games_played": 272,
        "win_rate": 0.46691176470588236
    },
    {
        "brawler": "COLETTE",
        "games_played": 11327,
        "win_rate": 0.4605809128630705
    },
    {
        "brawler": "EDGAR",
        "games_played": 132757,
        "win_rate": 0.46043523128723907
    },
    {
        "brawler": "PEARL",
        "games_played": 2876,
        "win_rate": 0.45966620305980527
    },
    {
        "brawler": "MORTIS",
        "games_played": 321535,
        "win_rate": 0.45612763773772685
    },
    {
        "brawler": "SHELLY",
        "games_played": 59583,
        "win_rate": 0.4530990383162983
    },
    {
        "brawler": "COLT",
        "games_played": 97360,
        "win_rate": 0.4528656532456861
    },
    {
        "brawler": "JESSIE",
        "games_played": 19703,
        "win_rate": 0.45155560066994876
    },
    {
        "brawler": "MEG",
        "games_played": 6993,
        "win_rate": 0.45087945087945086
    },
    {
        "brawler": "KIT",
        "games_played": 16626,
        "win_rate": 0.44436424876699143
    },
    {
        "brawler": "POCO",
        "games_played": 17630,
        "win_rate": 0.44288145207033464
    },
    {
        "brawler": "BELLE",
        "games_played": 796,
        "win_rate": 0.4396984924623116
    },
    {
        "brawler": "BYRON",
        "games_played": 2869,
        "win_rate": 0.4395259672359707
    },
    {
        "brawler": "LILY",
        "games_played": 11652,
        "win_rate": 0.43503261242705116
    },
    {
        "brawler": "BONNIE",
        "games_played": 710,
        "win_rate": 0.4309859154929577
    },
    {
        "brawler": "EMZ",
        "games_played": 11949,
        "win_rate": 0.42982676374592016
    },
    {
        "brawler": "CROW",
        "games_played": 27564,
        "win_rate": 0.42878392105645047
    },
    {
        "brawler": "BO",
        "games_played": 6189,
        "win_rate": 0.42834060429794796
    },
    {
        "brawler": "GUS",
        "games_played": 3828,
        "win_rate": 0.4203239289446186
    },
    {
        "brawler": "BROCK",
        "games_played": 8853,
        "win_rate": 0.41861515870326443
    },
    {
        "brawler": "CHUCK",
        "games_played": 295,
        "win_rate": 0.41694915254237286
    },
    {
        "brawler": "GENE",
        "games_played": 1405,
        "win_rate": 0.41352313167259785
    },
    {
        "brawler": "LEON",
        "games_played": 42754,
        "win_rate": 0.4063479440520185
    },
    {
        "brawler": "8-BIT",
        "games_played": 900,
        "win_rate": 0.40555555555555556
    },
    {
        "brawler": "MANDY",
        "games_played": 1336,
        "win_rate": 0.38547904191616766
    },
    {
        "brawler": "LOLA",
        "games_played": 477,
        "win_rate": 0.3668763102725367
    },
    {
        "brawler": "PIPER",
        "games_played": 4685,
        "win_rate": 0.3660618996798292
    },
    {
        "brawler": "ANGELO",
        "games_played": 529,
        "win_rate": 0.3383742911153119
    },
    {
        "brawler": "NANI",
        "games_played": 624,
        "win_rate": 0.32051282051282054
    }
]