[
    {
        "brawler": "ASH",
        "games_played": 140,
        "win_rate": 0.8
    },
    {
        "brawler": "CHARLIE",
        "games_played": 136,
        "win_rate": 0.7867647058823529
    },
    {
        "brawler": "BELLE",
        "games_played": 3224,
        "win_rate": 0.749379652605459
    },
    {
        "brawler": "BYRON",
        "games_played": 1601,
        "win_rate": 0.7133041848844472
    },
    {
        "brawler": "OTIS",
        "games_played": 520,
        "win_rate": 0.7115384615384616
    },
    {
        "brawler": "PAM",
        "games_played": 53,
        "win_rate": 0.6981132075471698
    },
    {
        "brawler": "RUFFS",
        "games_played": 388,
        "win_rate": 0.6958762886597938
    },
    {
        "brawler": "RICO",
        "games_played": 4333,
        "win_rate": 0.6935148857604431
    },
    {
        "brawler": "MOE",
        "games_played": 7077,
        "win_rate": 0.6908294475060054
    },
    {
        "brawler": "GUS",
        "games_played": 1643,
        "win_rate": 0.6871576384662204
    },
    {
        "brawler": "LOLA",
        "games_played": 498,
        "win_rate": 0.6867469879518072
    },
    {
        "brawler": "AMBER",
        "games_played": 527,
        "win_rate": 0.683111954459203
    },
    {
        "brawler": "BEA",
        "games_played": 2999,
        "win_rate": 0.6785595198399467
    },
    {
        "brawler": "BONNIE",
        "games_played": 272,
        "win_rate": 0.6764705882352942
    },
    {
        "brawler": "GRAY",
        "games_played": 141,
        "win_rate": 0.6737588652482269
    },
    {
        "brawler": "MAX",
        "games_played": 2963,
        "win_rate": 0.6429294633817078
    },
    {
        "brawler": "BUSTER",
        "games_played": 1017,
        "win_rate": 0.640117994100295
    },
    {
        "brawler": "SANDY",
        "games_played": 1275,
        "win_rate": 0.64
    },
    {
        "brawler": "R-T",
        "games_played": 127,
        "win_rate": 0.6299212598425197
    },
    {
        "brawler": "CARL",
        "games_played": 688,
        "win_rate": 0.6090116279069767
    },
    {
        "brawler": "JANET",
        "games_played": 313,
        "win_rate": 0.6070287539936102
    },
    {
        "brawler": "LOU",
        "games_played": 256,
        "win_rate": 0.6015625
    },
    {
        "brawler": "MELODIE",
        "games_played": 4331,
        "win_rate": 0.5915492957746479
    },
    {
        "brawler": "CHESTER",
        "games_played": 878,
        "win_rate": 0.5831435079726651
    },
    {
        "brawler": "MAISIE",
        "games_played": 867,
        "win_rate": 0.5594002306805075
    },
    {
        "brawler": "SPROUT",
        "games_played": 34,
        "win_rate": 0.5588235294117647
    },
    {
        "brawler": "MEG",
        "games_played": 1229,
        "win_rate": 0.5516680227827502
    },
    {
        "brawler": "PIPER",
        "games_played": 4472,
        "win_rate": 0.5476296958855098
    },
    {
        "brawler": "CORDELIUS",
        "games_played": 311,
        "win_rate": 0.5434083601286174
    },
    {
        "brawler": "COLETTE",
        "games_played": 766,
        "win_rate": 0.5365535248041775
    },
    {
        "brawler": "LARRY & LAWRIE",
        "games_played": 56,
        "win_rate": 0.5357142857142857
    },
    {
        "brawler": "DRACO",
        "games_played": 267,
        "win_rate": 0.5355805243445693
    },
    {
        "brawler": "PEARL",
        "games_played": 355,
        "win_rate": 0.5267605633802817
    },
    {
        "brawler": "GALE",
        "games_played": 3161,
        "win_rate": 0.5267320468206264
    },
    {
        "brawler": "KENJI",
        "games_played": 10656,
        "win_rate": 0.5231794294294294
    },
    {
        "brawler": "SAM",
        "games_played": 133,
        "win_rate": 0.518796992481203
    },
    {
        "brawler": "PENNY",
        "games_played": 2031,
        "win_rate": 0.5061546036435254
    },
    {
        "brawler": "STU",
        "games_played": 4451,
        "win_rate": 0.5039317007414065
    },
    {
        "brawler": "DARRYL",
        "games_played": 7089,
        "win_rate": 0.4968260685569192
    },
    {
        "brawler": "JUJU",
        "games_played": 117,
        "win_rate": 0.49572649572649574
    },
    {
        "brawler": "TARA",
        "games_played": 1920,
        "win_rate": 0.49375
    },
    {
        "brawler": "SPIKE",
        "games_played": 1131,
        "win_rate": 0.493368700265252
    },
    {
        "brawler": "MANDY",
        "games_played": 1773,
        "win_rate": 0.48336153412295546
    },
    {
        "brawler": "GRIFF",
        "games_played": 1015,
        "win_rate": 0.47881773399014776
    },
    {
        "brawler": "CLANCY",
        "games_played": 9042,
        "win_rate": 0.4786551647865516
    },
    {
        "brawler": "FANG",
        "games_played": 12025,
        "win_rate": 0.47301455301455303
    },
    {
        "brawler": "SQUEAK",
        "games_played": 574,
        "win_rate": 0.4686411149825784
    },
    {
        "brawler": "SURGE",
        "games_played": 4117,
        "win_rate": 0.46514452271071166
    },
    {
        "brawler": "MORTIS",
        "games_played": 10604,
        "win_rate": 0.4601093926820068
    },
    {
        "brawler": "JESSIE",
        "games_played": 3233,
        "win_rate": 0.45777915248994744
    },
    {
        "brawler": "8-BIT",
        "games_played": 876,
        "win_rate": 0.4531963470319635
    },
    {
        "brawler": "GENE",
        "games_played": 135,
        "win_rate": 0.45185185185185184
    },
    {
        "brawler": "LEON",
        "games_played": 3050,
        "win_rate": 0.4488524590163934
    },
    {
        "brawler": "COLT",
        "games_played": 8227,
        "win_rate": 0.4340585875774888
    },
    {
        "brawler": "BULL",
        "games_played": 323,
        "win_rate": 0.43343653250773995
    },
    {
        "brawler": "BROCK",
        "games_played": 899,
        "win_rate": 0.42936596218020023
    },
    {
        "brawler": "POCO",
        "games_played": 2903,
        "win_rate": 0.42094385118842575
    },
    {
        "brawler": "JACKY",
        "games_played": 1467,
        "win_rate": 0.4185412406271302
    },
    {
        "brawler": "BIBI",
        "games_played": 3076,
        "win_rate": 0.41482444733420026
    },
    {
        "brawler": "NITA",
        "games_played": 359,
        "win_rate": 0.41225626740947074
    },
    {
        "brawler": "EMZ",
        "games_played": 869,
        "win_rate": 0.4085155350978136
    },
    {
        "brawler": "CROW",
        "games_played": 4331,
        "win_rate": 0.40821981066728236
    },
    {
        "brawler": "BUZZ",
        "games_played": 1348,
        "win_rate": 0.4035608308605341
    },
    {
        "brawler": "EVE",
        "games_played": 51,
        "win_rate": 0.39215686274509803
    },
    {
        "brawler": "WILLOW",
        "games_played": 36,
        "win_rate": 0.3888888888888889
    },
    {
        "brawler": "ANGELO",
        "games_played": 377,
        "win_rate": 0.38461538461538464
    },
    {
        "brawler": "KIT",
        "games_played": 596,
        "win_rate": 0.3808724832214765
    },
    {
        "brawler": "EL PRIMO",
        "games_played": 860,
        "win_rate": 0.3802325581395349
    },
    {
        "brawler": "DOUG",
        "games_played": 150,
        "win_rate": 0.38
    },
    {
        "brawler": "MICO",
        "games_played": 69,
        "win_rate": 0.37681159420289856
    },
    {
        "brawler": "NANI",
        "games_played": 348,
        "win_rate": 0.3764367816091954
    },
    {
        "brawler": "FRANK",
        "games_played": 3004,
        "win_rate": 0.375832223701731
    },
    {
        "brawler": "BO",
        "games_played": 1031,
        "win_rate": 0.3734238603297769
    },
    {
        "brawler": "TICK",
        "games_played": 9544,
        "win_rate": 0.37332355406538137
    },
    {
        "brawler": "SHELLY",
        "games_played": 1633,
        "win_rate": 0.3717085119412125
    },
    {
        "brawler": "MR. P",
        "games_played": 315,
        "win_rate": 0.35555555555555557
    },
    {
        "brawler": "DYNAMIKE",
        "games_played": 442,
        "win_rate": 0.35294117647058826
    },
    {
        "brawler": "EDGAR",
        "games_played": 1593,
        "win_rate": 0.35279347143753925
    },
    {
        "brawler": "LILY",
        "games_played": 577,
        "win_rate": 0.34488734835355284
    },
    {
        "brawler": "HANK",
        "games_played": 27,
        "win_rate": 0.3333333333333333
    },
    {
        "brawler": "ROSA",
        "games_played": 34,
        "win_rate": 0.3235294117647059
    },
    {
        "brawler": "GROM",
        "games_played": 524,
        "win_rate": 0.31297709923664124
    },
    {
        "brawler": "BERRY",
        "games_played": 84,
        "win_rate": 0.27380952380952384
    },
    {
        "brawler": "BARLEY",
        "games_played": 21,
        "win_rate": 0.23809523809523808
    },
    {
        "brawler": "CHUCK",
        "games_played": 14,
        "win_rate": 0.14285714285714285
    }
]